pyctramer/AnalyzeQC.py
pyctramer/ConstructFF.py
pyctramer/FGR.py
pyctramer/JobControl.py
pyctramer/MarcusAA.py
pyctramer/PyCTRAMER.py
pyctramer/RunMD.py
pyctramer/SpinBoson.py
pyctramer/SubmitQC.py
pyctramer/Utilities.py
pyctramer/__init__.py
pyctramer/pyctramer.py
pyctramer-0.2.8.dist-info/METADATA
pyctramer-0.2.8.dist-info/WHEEL
pyctramer-0.2.8.dist-info/top_level.txt
pyctramer-0.2.8.dist-info/RECORD
