Metadata-Version: 2.1
Name: pyctramer
Version: 0.2.8
Summary: Python package for Charge Transfer Rate from Atomistic Molecular dynamics, Electronic structure, and Rate theory
Home-page: https://www.github.com/ctramer/PyCTRAMER
Author: Zengkui Liu, Dominikus Brian, and Xiang Sun
Author-email: zengkui.liu@nyu.edu
